README.rst
setup.py
pacscopy/__init__.py
pacscopy/pacscopy.py
pacscopy.egg-info/PKG-INFO
pacscopy.egg-info/SOURCES.txt
pacscopy.egg-info/dependency_links.txt
pacscopy.egg-info/not-zip-safe
pacscopy.egg-info/requires.txt
pacscopy.egg-info/top_level.txt