Metadata-Version: 1.0
Name: pacscopy
Version: 1.0.2
Summary: copy from (openstorage) to output directory
Home-page: https://github.com/FNNDSC/pl-pacscopy
Author: Rudolph Pienaar
Author-email: rudolph.pienaar@gmail.com
License: MIT
Platform: UNKNOWN
